[
    {
      "name": "Доставка строительных материалов для нового проекта",
      "description": "Организация доставки строительных материалов на объект строительства.",
      "tenderId": "488a68bf-951f-44e0-ad96-f61d74f693b5",  // Доставка стройматериалов для нового проекта
      "authorType": "Organization",
      "authorId": "3d17db5f-c152-4a1b-ad3b-4f1210ffa0a9"  // Сергей Сергеев, Строительная компания "ГрандСтрой", LLC
    },
    {
      "name": "Строительство нового жилого комплекса",
      "description": "Проект по строительству многоквартирного жилого комплекса в центре города.",
      "tenderId": "4dbf76b6-4614-42f2-9e34-4f2e02065a4c",  // Строительство нового жилого комплекса
      "authorType": "Organization",
      "authorId": "a2572579-8502-472d-a24c-f9684fbf0498"  // Екатерина Иванова, Транспортная компания "Быстрая Доставка", IE
    },
    {
      "name": "Строительство торгового центра",
      "description": "Проектирование и строительство нового торгового центра на окраине города.",
      "tenderId": "5852152d-3d30-461e-9500-0a0a491e80d7",  // Строительство торгового центра
      "authorType": "Organization",
      "authorId": "9c139a52-8023-40ac-992b-1dfdc902ace2"  // Федор Федоров, Производственная фирма "УпаковкаПром", JSC
    },
    {
      "name": "Экспресс-доставка товаров для интернет-магазина",
      "description": "Срочная доставка товаров по заказам интернет-магазина.",
      "tenderId": "64b321f1-a374-4ac9-bbf0-fe830ff105dc",  // Экспресс-доставка товаров для интернет-магазина
      "authorType": "Organization",
      "authorId": "9bc11466-f256-4eff-8394-f33136cc3a38"  // Алина Васильева, Курьерская служба "ЭкспрессПост", LLC
    },
    {
      "name": "Производство упаковочных материалов",
      "description": "Производство и поставка упаковочных материалов для новых продуктов.",
      "tenderId": "7663c3de-a654-42c4-a020-bc85f32a11df",  // Производство упаковочных материалов
      "authorType": "Organization",
      "authorId": "75048ece-9e93-428b-8764-99d7bc3d15fd"  // Николай Попов, Клининговая компания "Чистый Офис", IE
    },
    {
      "name": "Клининговые услуги для офисных помещений",
      "description": "Услуги по уборке и чистке офисных помещений и торговых площадей.",
      "tenderId": "77548b27-7c6f-471b-b613-90356433dea7",  // Клининговые услуги для офисных помещений
      "authorType": "Organization",
      "authorId": "6e562d61-6da0-4113-b079-395c5b858069"  // Татьяна Козлова, Строительная компания "АрхСтрой", JSC
    },
    {
      "name": "Строительство нового торгового центра",
      "description": "Проект и строительство современного торгового центра в центре города.",
      "tenderId": "86e4424a-7453-4198-8fcc-70a9675b5ad2",  // Строительство нового торгового центра
      "authorType": "Organization",
      "authorId": "7dec35f9-5b66-4396-8ee3-6811eda1e639"  // Андрей Зубов, Компания "БезопасностьПро", LLC
    },
    {
      "name": "Доставка оборудования для фабрики",
      "description": "Услуги по доставке нового оборудования для производственной фабрики.",
      "tenderId": "8c3fabe0-ba12-47b8-be7b-9ddf4fe7b790",  // Доставка оборудования для фабрики
      "authorType": "Organization",
      "authorId": "92128edf-dc65-4501-a322-c54db9f8b93a"  // Ирина Лебедева, Логистическая компания "СтройЛогистик", JSC
    },
    {
      "name": "Проектирование системы безопасности",
      "description": "Проектирование и внедрение системы безопасности для крупного завода.",
      "tenderId": "d1c70cec-e21a-43b0-b809-38fe679d33d1",  // Проектирование системы безопасности
      "authorType": "Organization",
      "authorId": "b374e354-20cd-48a3-8406-3b1f8aa51823"  // Александр Воронов, IT-компания "СкладСофт", LLC
    },
    {
      "name": "Разработка программного обеспечения для управления складами",
      "description": "Создание ПО для управления складскими запасами и логистики.",
      "tenderId": "fff94208-aab6-4300-97d7-4f8e21689134",  // Разработка программного обеспечения для управления складами
      "authorType": "Organization",
      "authorId": "047c50bd-72c3-4485-982a-bfd48e155fd5"  // Наталья Соболева, Торговый дом "ГлобусСтрой", IE
    }
  ]
  